AndroidKaifaRumenjiaochengCYuyanBianchengWangFix1/README.md
AndroidKaifaRumenjiaochengCYuyanBianchengWangFix1/__init__.py
AndroidKaifaRumenjiaochengCYuyanBianchengWangFix1/__main__.py
AndroidKaifaRumenjiaochengCYuyanBianchengWangFix1/file.epub
AndroidKaifaRumenjiaochengCYuyanBianchengWangFix1/index.html
AndroidKaifaRumenjiaochengCYuyanBianchengWangFix1/css/__init__.py
AndroidKaifaRumenjiaochengCYuyanBianchengWangFix1/css/annotations.css
AndroidKaifaRumenjiaochengCYuyanBianchengWangFix1/css/main.css
AndroidKaifaRumenjiaochengCYuyanBianchengWangFix1/css/normalize.css
AndroidKaifaRumenjiaochengCYuyanBianchengWangFix1/css/popup.css
AndroidKaifaRumenjiaochengCYuyanBianchengWangFix1/font/__init__.py
AndroidKaifaRumenjiaochengCYuyanBianchengWangFix1/font/fontello.eot
AndroidKaifaRumenjiaochengCYuyanBianchengWangFix1/font/fontello.svg
AndroidKaifaRumenjiaochengCYuyanBianchengWangFix1/font/fontello.ttf
AndroidKaifaRumenjiaochengCYuyanBianchengWangFix1/font/fontello.woff
AndroidKaifaRumenjiaochengCYuyanBianchengWangFix1/img/__init__.py
AndroidKaifaRumenjiaochengCYuyanBianchengWangFix1/img/annotator-glyph-sprite.png
AndroidKaifaRumenjiaochengCYuyanBianchengWangFix1/img/annotator-icon-sprite.png
AndroidKaifaRumenjiaochengCYuyanBianchengWangFix1/img/apple-touch-icon.png
AndroidKaifaRumenjiaochengCYuyanBianchengWangFix1/img/cancelfullscreen.png
AndroidKaifaRumenjiaochengCYuyanBianchengWangFix1/img/close.png
AndroidKaifaRumenjiaochengCYuyanBianchengWangFix1/img/fullscreen.png
AndroidKaifaRumenjiaochengCYuyanBianchengWangFix1/img/loader.gif
AndroidKaifaRumenjiaochengCYuyanBianchengWangFix1/img/menu-icon.png
AndroidKaifaRumenjiaochengCYuyanBianchengWangFix1/img/save.png
AndroidKaifaRumenjiaochengCYuyanBianchengWangFix1/img/saved.png
AndroidKaifaRumenjiaochengCYuyanBianchengWangFix1/img/settings-s.png
AndroidKaifaRumenjiaochengCYuyanBianchengWangFix1/img/settings.png
AndroidKaifaRumenjiaochengCYuyanBianchengWangFix1/img/star.png
android_kaifa_rumenjiaocheng_c_yuyan_biancheng_wang_fix1-2025.3.23.0.dist-info/METADATA
android_kaifa_rumenjiaocheng_c_yuyan_biancheng_wang_fix1-2025.3.23.0.dist-info/WHEEL
android_kaifa_rumenjiaocheng_c_yuyan_biancheng_wang_fix1-2025.3.23.0.dist-info/entry_points.txt
android_kaifa_rumenjiaocheng_c_yuyan_biancheng_wang_fix1-2025.3.23.0.dist-info/top_level.txt
android_kaifa_rumenjiaocheng_c_yuyan_biancheng_wang_fix1-2025.3.23.0.dist-info/RECORD
